defn_cdktf_provider_boundary/__init__.py
defn_cdktf_provider_boundary/main.py
defn_cdktf_provider_boundary/_jsii/__init__.py
defn_cdktf_provider_boundary/_jsii/hashicorp_boundary@0.0.0.jsii.tgz
defn_cdktf_provider_boundary/_jsii/main.py
defn_cdktf_provider_boundary-0.4.1.dist-info/METADATA
defn_cdktf_provider_boundary-0.4.1.dist-info/WHEEL
defn_cdktf_provider_boundary-0.4.1.dist-info/namespace_packages.txt
defn_cdktf_provider_boundary-0.4.1.dist-info/top_level.txt
defn_cdktf_provider_boundary-0.4.1.dist-info/RECORD
